{
  "kind": "collectionType",
  "collectionName": "firmwares",
  "info": {
    "singularName": "firmware",
    "pluralName": "firmwares",
    "displayName": "Firmware"
  },
  "options": {
    "draftAndPublish": true
  },
  "attributes": {
    "model": {
      "type": "string",
      "required": true
    },
    "version": {
      "type": "string"
    },
    "releaseDate": {
      "type": "date"
    },
    "releaseNotes": {
      "type": "text"
    },
    "file": {
      "type": "media",
      "multiple": false,
      "allowedTypes": [
        "files"
      ]
    }
  }
}
